ewelink/__init__.py
ewelink/ewelink.py
ewelink/py.typed
ewelink/types.py
ewelink-0.2.1.dist-info/LICENSE.md
ewelink-0.2.1.dist-info/METADATA
ewelink-0.2.1.dist-info/WHEEL
ewelink-0.2.1.dist-info/top_level.txt
ewelink-0.2.1.dist-info/RECORD
